MipsSim/Design.v
module pipelined_mips (clk1,clk2);

  input clk1,clk2;    //2 phase clk

  parameter R_format=6'b000000,lw=6'b100011,sw=6'b101011,
  beq=6'b000100,bne=6'b000101,j=6'b000010,jal=6'b000011,
  addi=6'b001000,andi=6'b001100,ori=6'b001101,xori=6'b001110,
  slti=6'b001010,lui=6'b001111,hlt=6'b111111;
  parameter jr_func=8;
  ////////////////////////////////////////////////////////////////////////////////
  reg halted , branch_taken;// special regs for hlt and indicating jump/branches
  //// inbetween stages registers
  reg [31:0] IF_ID_IR, ID_EX_IR, EX_MEM_IR, MEM_WB_IR,IF_ID_NPC, ID_EX_NPC,
  			 EX_MEM_NPC,MEM_WB_NPC,ID_EX_A,ID_EX_B,ID_EX_IMM,EX_MEM_ALUresult,
  			EX_MEM_A,EX_MEM_B,EX_MEM_BranchAdrr,MEM_WB_RDM,MEM_WB_ALUresult
  			,EX_MEM_JumpAdrr;
                  
  //////////////////////////////////////////////////////////////////////////////
  reg [31:0]  I_memory [0:8191];  // declaration of instruction mem of size 4KB 
  reg [31:0]  D_memory [0:8191];  // declaration of data mem of size 4KB 
  reg [31:0] reg_file[0:31]; 
  reg [31:0] pc;
////////////////////////////////////////////////////////////
  //stage 1 */ Instruction fetch (IF) /*////////////////////
  always @(posedge clk1)
    begin 
    	branch_taken<=#2  0;
      if (halted==0)
        begin
         
             // 	jump_taken<=#2 0;
          if (((EX_MEM_ALUresult==0)&&(EX_MEM_IR[31:26]==beq)) ||
              ((EX_MEM_ALUresult!=0)&&(EX_MEM_IR[31:26]==bne)) )     
          begin// if instruction being executed is bne or beq
          		IF_ID_NPC <=#2  EX_MEM_BranchAdrr+4;
         IF_ID_IR <= #2 I_memory[({2'b00,EX_MEM_BranchAdrr[31:2]})];
            	pc<=#2 EX_MEM_BranchAdrr+4;//>>2for byte addressed mem
            	branch_taken<=#2 1;
          end
          
          else if ((EX_MEM_IR[31:26]==j)||(EX_MEM_IR[31:26]==jal))
          begin		// if instruction being executed is jump/jal
          		IF_ID_NPC <=#2 EX_MEM_JumpAdrr+4;
          IF_ID_IR <=#2  I_memory[({2'b00,EX_MEM_JumpAdrr[31:2]})];
            pc<=#2 EX_MEM_JumpAdrr+4; 
             	branch_taken<=#2 1;
          end
          
          else if ( (EX_MEM_IR[5:0]==jr_func)&&(EX_MEM_IR[31:26]==0) )
          begin           // if instruction being executed is jr
            	IF_ID_NPC <=#2 EX_MEM_A+4;
            IF_ID_IR <=#2  I_memory[({2'b00,EX_MEM_A[31:2]})];
            	pc<=#2 EX_MEM_A+4;
             	branch_taken<=#2 1;
          end
           
          else // if instruction being executed is nonbranching inst.
          begin
          		IF_ID_NPC <=#2  pc+4;
            IF_ID_IR <= #2 I_memory[({2'b00,pc[31:2]})];
           	pc<=#2 pc+4;
            
          end       
            
        end
     end
////////////////////////////////////////////////////////////
 
  //stage 2 */ Instruction decode and reg fetch (ID) /*////
  always @(posedge clk2)
    begin 
      if (halted==0)
        begin
      	  ID_EX_IR<=#2 IF_ID_IR;
          ID_EX_NPC<=#2 IF_ID_NPC;
          ID_EX_IMM <= #2 {{16{IF_ID_IR[15]}},{IF_ID_IR[15:0]}};
          //extending imm field to 32 bits
          
          if (IF_ID_IR[25:21]==5'b00000)//tryin to access reg zero?!
            ID_EX_A <=#2  0;//else read1_A=reg_file[reg_address]
          else ID_EX_A <=#2 reg_file[IF_ID_IR[25:21]];
        
          if (IF_ID_IR[20:16]==5'b00000)//tryin to access reg zero?!
            ID_EX_B <=#2  0;//else read2_B=reg_file[reg_address]
          else ID_EX_B <=#2  reg_file[IF_ID_IR[20:16]];
     
        
        end
    end
///////////////////////////////////////////////////////////
  //stage 3 */ execution and effective addr calc (EX) /*////
  always @(posedge clk1)
    begin 
      if (halted==0)
        begin
      	 	    	
      
          EX_MEM_ALUresult<=#2 32'hDEADBEEF;//initialization(avoid latching)
          case (ID_EX_IR[31:26])//opcode
	        R_format:
	        begin
              case (ID_EX_IR[5:0]) //func
                //shamt=ID_EX_IR[10:6]
	         0:	EX_MEM_ALUresult<=#2 ID_EX_B<<ID_EX_IR[10:6] ; 	//sll
	         2:	EX_MEM_ALUresult<=#2 ID_EX_B>>ID_EX_IR[10:6] ; 	//srl
             3:	EX_MEM_ALUresult<=#2 $signed(ID_EX_B)>>>ID_EX_IR[10:6] ; 	//sra
	            32: EX_MEM_ALUresult<=#2 ID_EX_A+ID_EX_B ;	//add
	            34: EX_MEM_ALUresult<=#2 ID_EX_A-ID_EX_B ; 	//sub
	            36: EX_MEM_ALUresult<=#2 ID_EX_A&ID_EX_B ; 	//and
	            37: EX_MEM_ALUresult<=#2 ID_EX_A|ID_EX_B ; 	//or
	            38: EX_MEM_ALUresult<=#2 ID_EX_A^ID_EX_B ; 	//xor
                39: EX_MEM_ALUresult<=#2  ~(ID_EX_A|ID_EX_B) ; 	//nor
	            42: EX_MEM_ALUresult<=#2 $signed(ID_EX_A)<$signed(ID_EX_B) ; 	//slt
	            endcase
	        end

	        addi,lw,sw: EX_MEM_ALUresult<=#2 ID_EX_A+ID_EX_IMM; //addi, loads, stores
	        beq,bne: EX_MEM_ALUresult<=#2 ID_EX_A-ID_EX_B; //beq, bne
	        andi: EX_MEM_ALUresult<=#2 ID_EX_A&ID_EX_IMM; //andi
	        ori: EX_MEM_ALUresult<=#2 ID_EX_A|ID_EX_IMM; //ori
	        xori: EX_MEM_ALUresult<=#2 ID_EX_A^ID_EX_IMM; //xori
	        slti: EX_MEM_ALUresult<=#2 $signed(ID_EX_A)<$signed(ID_EX_IMM); //slti
	        lui: EX_MEM_ALUresult<=#2 ID_EX_IMM<<16; //lui
        endcase
         EX_MEM_IR<=#2 ID_EX_IR;
         	EX_MEM_NPC<=#2 ID_EX_NPC;
			EX_MEM_A<=#2 ID_EX_A;
         	EX_MEM_B<=#2 ID_EX_B;
            EX_MEM_BranchAdrr<=#2 ID_EX_NPC+(ID_EX_IMM<<2);
          EX_MEM_JumpAdrr<=#2 {ID_EX_NPC[31:28],ID_EX_IR[25:0],2'b00};
        end
    end
///////////////////////////////////////////////////////////
 
  //stage 4 */ Memory access and branch checking (MEM) /*////
  always @(posedge clk2)
    begin 
      if (halted==0)
        begin
      
          if (EX_MEM_IR[31:26]==lw)
            MEM_WB_RDM<=#2 D_memory[EX_MEM_ALUresult>>2];
          
          else if((EX_MEM_IR[31:26]==sw)&&(branch_taken==0))
					//disable writing if there is abranch
            D_memory[EX_MEM_ALUresult>>2]<=#2 EX_MEM_B;
      
        	MEM_WB_IR<=#2 EX_MEM_IR;
        MEM_WB_NPC<=#2 EX_MEM_NPC;
          MEM_WB_ALUresult<=#2 EX_MEM_ALUresult;
          
        end
    end
///////////////////////////////////////////////////////////
  
  //stage 5  register write back stage (WB) ///////////
  always @(posedge clk1)
    begin
      if (branch_taken==0)
         	 begin
        case (MEM_WB_IR[31:26])
          hlt : halted<=#2 1'b1;
          R_format : reg_file [MEM_WB_IR[15:11]]<=#2 MEM_WB_ALUresult;
  addi,andi,slti,ori,xori,lui : reg_file [MEM_WB_IR[20:16]]<=#2 MEM_WB_ALUresult;
          lw :  reg_file [MEM_WB_IR[20:16]]<=#2 MEM_WB_RDM;
            jal : reg_file[31]<=#2 MEM_WB_NPC;//current pc+4
           
                
            endcase
    end
    end
///////////////////////////////////////////////////////////


endmodule

MipsSim/testbench-1.v
`include"Design.v"
module testbench ();
  
	reg clk1,clk2;
	integer i;
	integer j;
	integer k;
	integer file;
	integer file2;
	integer file3;
	
  pipelined_mips mips(clk1,clk2);
  
  initial///initializng to zero and generating clk
  	begin
      
      clk1=0;clk2=0;
      mips.halted=0;
     mips.branch_taken=0;
    //  mips.jump_taken=0;
      mips.pc=0;
     mips.reg_file[28]=32'h00000000;//initializing $gp
  
      forever
        begin
        #5 clk1=1; #5clk1=0;//2phase clk
       #5 clk2=1; #5clk2=0;
        
        end
      
    end

 
  
  initial 
  begin
    ///dumping to GTK wave
   
   	$readmemb("machine.txt",mips.I_memory);
  file=$fopen("memory1.txt");
   file2=$fopen("register1.txt");
   file3=$fopen("pc1.txt");

 
		


#49998 for(j=0;j<8192;j=j+1)
        begin
           $fwrite(file ,"%b \n",mips.D_memory[j]); 
           if(mips.I_memory[j] ==32'hffffffff)
           begin
             mips.pc = j*4;
           end
        end

	
 for(k=0;k<32;k=k+1)
	$fwrite(file2,"%b \n",mips.reg_file[k]);
	
	$fwrite(file3,"%b \n",mips.pc);

			

    end
	 initial 
	 begin
 $dumpfile ("mips.vcd");
 $dumpvars (0,testbench);
 #50000 $finish;
	 end
	 
endmodule

MipsSim/mips.vcd
$date
	Sat Nov 16 20:56:35 2019
$end
$version
	Icarus Verilog
$end
$timescale
	1s
$end
$scope module testbench $end
$var reg 1 ! clk1 $end
$var reg 1 " clk2 $end
$var integer 32 # file [31:0] $end
$var integer 32 $ file2 [31:0] $end
$var integer 32 % file3 [31:0] $end
$var integer 32 & j [31:0] $end
$var integer 32 ' k [31:0] $end
$scope module mips $end
$var wire 1 ! clk1 $end
$var wire 1 " clk2 $end
$var reg 32 ( EX_MEM_A [31:0] $end
$var reg 32 ) EX_MEM_ALUresult [31:0] $end
$var reg 32 * EX_MEM_B [31:0] $end
$var reg 32 + EX_MEM_BranchAdrr [31:0] $end
$var reg 32 , EX_MEM_IR [31:0] $end
$var reg 32 - EX_MEM_JumpAdrr [31:0] $end
$var reg 32 . EX_MEM_NPC [31:0] $end
$var reg 32 / ID_EX_A [31:0] $end
$var reg 32 0 ID_EX_B [31:0] $end
$var reg 32 1 ID_EX_IMM [31:0] $end
$var reg 32 2 ID_EX_IR [31:0] $end
$var reg 32 3 ID_EX_NPC [31:0] $end
$var reg 32 4 IF_ID_IR [31:0] $end
$var reg 32 5 IF_ID_NPC [31:0] $end
$var reg 32 6 MEM_WB_ALUresult [31:0] $end
$var reg 32 7 MEM_WB_IR [31:0] $end
$var reg 32 8 MEM_WB_NPC [31:0] $end
$var reg 32 9 MEM_WB_RDM [31:0] $end
$var reg 1 : branch_taken $end
$var reg 1 ; halted $end
$var reg 32 < pc [31:0] $end
$upscope $end
$upscope $end
$enddefinitions $end
#0
$dumpvars
b0 <
0;
0:
bx 9
bx 8
bx 7
bx 6
bx 5
bx 4
bx 3
bx 2
bx 1
bx 0
bx /
bx .
bx -
bx ,
bx +
bx *
bx )
bx (
bx '
bx &
b1000 %
b100 $
b10 #
0"
0!
$end
#5
1!
#7
b100 <
b100000000100001111111111111001 4
b100 5
bx00 -
b11011110101011011011111011101111 )
#10
0!
#15
1"
#17
b0 /
b11111111111111111111111111111001 1
b100 3
b100000000100001111111111111001 2
b11011110101011011011111011101111 6
#20
0"
#25
1!
#27
b10000111111111111100100 -
b11111111111111111111111111101000 +
b0 (
b100 .
b100000000100001111111111111001 ,
b11111111111111111111111111111001 )
b1000 <
b100000000100010000000000000000 4
b1000 5
#30
0!
#35
1"
#37
b11111111111111111111111111111001 6
b100 8
b100000000100001111111111111001 7
b0 1
b1000 3
b100000000100010000000000000000 2
#40
0"
#45
1!
#47
b1100 <
b100000100000000100000 4
b1100 5
b10001000000000000000000 -
b1000 +
b1000 .
b100000000100010000000000000000 ,
b0 )
#50
0!
#55
1"
#57
b11111111111111111111111111111001 0
b100000000100000 1
b1100 3
b100000100000000100000 2
b0 6
b1000 8
b100000000100010000000000000000 7
#60
0"
#65
1!
#67
b10000010000000010000000 -
b10000000010001100 +
b11111111111111111111111111111001 *
b1100 .
b100000100000000100000 ,
b11111111111111111111111111111001 )
b10000 <
b100010100100000100000 4
b10000 5
#70
0!
#75
1"
#77
b11111111111111111111111111111001 6
b1100 8
b100000100000000100000 7
b0 0
b100100000100000 1
b10000 3
b100010100100000100000 2
#80
0"
#85
1!
#87
b10100 <
b100000000010101000000000000000 4
b10100 5
b10001010010000010000000 -
b10010000010010000 +
b0 *
b10000 .
b100010100100000100000 ,
b0 )
#90
0!
#95
1"
#97
bx 0
b11111111111111111000000000000000 1
b10100 3
b100000000010101000000000000000 2
b0 6
b10000 8
b100010100100000100000 7
#100
0"
#105
1!
#107
b1010100000000000000000 -
b11111111111111100000000000010100 +
bx *
b10100 .
b100000000010101000000000000000 ,
b11111111111111111000000000000000 )
b11000 <
b111100000010101000000000000000 4
b11000 5
#110
0!
#115
1"
#117
b11111111111111111000000000000000 6
b10100 8
b100000000010101000000000000000 7
b11000 3
b111100000010101000000000000000 2
#120
0"
#125
1!
#127
b11100 <
b0 4
b11100 5
b11111111111111100000000000011000 +
b11000 .
b111100000010101000000000000000 ,
b10000000000000000000000000000000 )
#130
0!
#135
1"
#137
b0 0
b0 1
b11100 3
b0 2
b10000000000000000000000000000000 6
b11000 8
b111100000010101000000000000000 7
#140
0"
#145
1!
#147
b0 -
b11100 +
b0 *
b11100 .
b0 ,
b0 )
b100000 <
b1010010000101100000100100 4
b100000 5
#150
0!
#155
1"
#157
b0 6
b11100 8
b0 7
b11111111111111111111111111111001 0
b10000000000000000000000000000000 /
b101100000100100 1
b100000 3
b1010010000101100000100100 2
#160
0"
#165
1!
#167
b100100 <
b0 4
b100100 5
b101001000010110000010010000 -
b10110000010110000 +
b11111111111111111111111111111001 *
b10000000000000000000000000000000 (
b100000 .
b1010010000101100000100100 ,
b10000000000000000000000000000000 )
#170
0!
#175
1"
#177
b0 0
b0 /
b0 1
b100100 3
b0 2
b10000000000000000000000000000000 6
b100000 8
b1010010000101100000100100 7
#180
0"
#185
1!
#187
b0 -
b100100 +
b0 *
b0 (
b100100 .
b0 ,
b0 )
b101000 <
b10001011000000000000000000101 4
b101000 5
#190
0!
#195
1"
#197
b0 6
b100100 8
b0 7
b10000000000000000000000000000000 /
b101 1
b101000 3
b10001011000000000000000000101 2
#200
0"
#205
1!
#207
b101100 <
b1000010010110000000101010 4
b101100 5
b101100000000000000000010100 -
b111100 +
b10000000000000000000000000000000 (
b101000 .
b10001011000000000000000000101 ,
b10000000000000000000000000000000 )
#210
0!
#215
1"
#217
b11111111111111111111111111111001 /
b110000000101010 1
b101100 3
b1000010010110000000101010 2
b10000000000000000000000000000000 6
b101000 8
b10001011000000000000000000101 7
#220
0"
#225
1!
#227
b100001001011000000010101000 -
b11000000011010100 +
b11111111111111111111111111111001 (
b101100 .
b1000010010110000000101010 ,
b1 )
b110000 <
b0 4
b110000 5
#230
0!
#235
1"
#237
b1 6
b101100 8
b1000010010110000000101010 7
b0 /
b0 1
b110000 3
b0 2
#240
0"
#245
1!
#247
b110100 <
b10001100000000000000000000111 4
b110100 5
b0 -
b110000 +
b0 (
b110000 .
b0 ,
b0 )
#250
0!
#255
1"
#257
b1 /
b111 1
b110100 3
b10001100000000000000000000111 2
b0 6
b110000 8
b0 7
#260
0"
#265
1!
#267
b110000000000000000000011100 -
b1010000 +
b1 (
b110100 .
b10001100000000000000000000111 ,
b1 )
b111000 <
b100001001010011111111111111111 4
b111000 5
#270
0!
#275
1"
#277
b1 6
b110100 8
b10001100000000000000000000111 7
b0 /
b11111111111111111111111111111111 1
b111000 3
b100001001010011111111111111111 2
#280
0"
#285
1!
#287
b111100 <
b1000000000000000000000001010 4
b111100 5
b100101001111111111111111100 -
b110100 +
b0 (
b111000 .
b100001001010011111111111111111 ,
b11111111111111111111111111111111 )
#290
0!
#295
1"
#297
b1010 1
b111100 3
b1000000000000000000000001010 2
b11111111111111111111111111111111 6
b111000 8
b100001001010011111111111111111 7
#300
0"
#305
1!
#307
b101000 -
b1100100 +
b111100 .
b1000000000000000000000001010 ,
b11011110101011011011111011101111 )
b1000000 <
b1001010000110100000101010 4
b1000000 5
#310
0!
#315
1"
#317
b11011110101011011011111011101111 6
b111100 8
b1000000000000000000000001010 7
b11111111111111111111111111111001 0
b11111111111111111111111111111111 /
b110100000101010 1
b1000000 3
b1001010000110100000101010 2
#320
0"
#325
1!
#327
1:
b101100 <
b1000010010110000000101010 4
b101100 5
b100101000011010000010101000 -
b11010000011101000 +
b11111111111111111111111111111001 *
b11111111111111111111111111111111 (
b1000000 .
b1001010000110100000101010 ,
b0 )
#330
0!
#335
1"
#337
b11111111111111111111111111111111 0
b11111111111111111111111111111001 /
b110000000101010 1
b101100 3
b1000010010110000000101010 2
b0 6
b1000000 8
b1001010000110100000101010 7
#340
0"
#345
1!
#347
b100001001011000000010101000 -
b11000000011010100 +
b11111111111111111111111111111111 *
b11111111111111111111111111111001 (
b101100 .
b1000010010110000000101010 ,
b1 )
b110000 <
b0 4
b110000 5
0:
#350
0!
#355
1"
#357
b1 6
b101100 8
b1000010010110000000101010 7
b0 0
b0 /
b0 1
b110000 3
b0 2
#360
0"
#365
1!
#367
b110100 <
b10001100000000000000000000111 4
b110100 5
b0 -
b110000 +
b0 *
b0 (
b110000 .
b0 ,
b0 )
#370
0!
#375
1"
#377
b1 /
b111 1
b110100 3
b10001100000000000000000000111 2
b0 6
b110000 8
b0 7
#380
0"
#385
1!
#387
b110000000000000000000011100 -
b1010000 +
b1 (
b110100 .
b10001100000000000000000000111 ,
b1 )
b111000 <
b100001001010011111111111111111 4
b111000 5
#390
0!
#395
1"
#397
b1 6
b110100 8
b10001100000000000000000000111 7
b11111111111111111111111111111111 0
b11111111111111111111111111111111 /
b11111111111111111111111111111111 1
b111000 3
b100001001010011111111111111111 2
#400
0"
#405
1!
#407
b111100 <
b1000000000000000000000001010 4
b111100 5
b100101001111111111111111100 -
b110100 +
b11111111111111111111111111111111 *
b11111111111111111111111111111111 (
b111000 .
b100001001010011111111111111111 ,
b11111111111111111111111111111110 )
#410
0!
#415
1"
#417
b0 0
b0 /
b1010 1
b111100 3
b1000000000000000000000001010 2
b11111111111111111111111111111110 6
b111000 8
b100001001010011111111111111111 7
#420
0"
#425
1!
#427
b101000 -
b1100100 +
b0 *
b0 (
b111100 .
b1000000000000000000000001010 ,
b11011110101011011011111011101111 )
b1000000 <
b1001010000110100000101010 4
b1000000 5
#430
0!
#435
1"
#437
b11011110101011011011111011101111 6
b111100 8
b1000000000000000000000001010 7
b11111111111111111111111111111001 0
b11111111111111111111111111111110 /
b110100000101010 1
b1000000 3
b1001010000110100000101010 2
#440
0"
#445
1!
#447
1:
b101100 <
b1000010010110000000101010 4
b101100 5
b100101000011010000010101000 -
b11010000011101000 +
b11111111111111111111111111111001 *
b11111111111111111111111111111110 (
b1000000 .
b1001010000110100000101010 ,
b0 )
#450
0!
#455
1"
#457
b11111111111111111111111111111110 0
b11111111111111111111111111111001 /
b110000000101010 1
b101100 3
b1000010010110000000101010 2
b0 6
b1000000 8
b1001010000110100000101010 7
#460
0"
#465
1!
#467
b100001001011000000010101000 -
b11000000011010100 +
b11111111111111111111111111111110 *
b11111111111111111111111111111001 (
b101100 .
b1000010010110000000101010 ,
b1 )
b110000 <
b0 4
b110000 5
0:
#470
0!
#475
1"
#477
b1 6
b101100 8
b1000010010110000000101010 7
b0 0
b0 /
b0 1
b110000 3
b0 2
#480
0"
#485
1!
#487
b110100 <
b10001100000000000000000000111 4
b110100 5
b0 -
b110000 +
b0 *
b0 (
b110000 .
b0 ,
b0 )
#490
0!
#495
1"
#497
b1 /
b111 1
b110100 3
b10001100000000000000000000111 2
b0 6
b110000 8
b0 7
#500
0"
#505
1!
#507
b110000000000000000000011100 -
b1010000 +
b1 (
b110100 .
b10001100000000000000000000111 ,
b1 )
b111000 <
b100001001010011111111111111111 4
b111000 5
#510
0!
#515
1"
#517
b1 6
b110100 8
b10001100000000000000000000111 7
b11111111111111111111111111111110 0
b11111111111111111111111111111110 /
b11111111111111111111111111111111 1
b111000 3
b100001001010011111111111111111 2
#520
0"
#525
1!
#527
b111100 <
b1000000000000000000000001010 4
b111100 5
b100101001111111111111111100 -
b110100 +
b11111111111111111111111111111110 *
b11111111111111111111111111111110 (
b111000 .
b100001001010011111111111111111 ,
b11111111111111111111111111111101 )
#530
0!
#535
1"
#537
b0 0
b0 /
b1010 1
b111100 3
b1000000000000000000000001010 2
b11111111111111111111111111111101 6
b111000 8
b100001001010011111111111111111 7
#540
0"
#545
1!
#547
b101000 -
b1100100 +
b0 *
b0 (
b111100 .
b1000000000000000000000001010 ,
b11011110101011011011111011101111 )
b1000000 <
b1001010000110100000101010 4
b1000000 5
#550
0!
#555
1"
#557
b11011110101011011011111011101111 6
b111100 8
b1000000000000000000000001010 7
b11111111111111111111111111111001 0
b11111111111111111111111111111101 /
b110100000101010 1
b1000000 3
b1001010000110100000101010 2
#560
0"
#565
1!
#567
1:
b101100 <
b1000010010110000000101010 4
b101100 5
b100101000011010000010101000 -
b11010000011101000 +
b11111111111111111111111111111001 *
b11111111111111111111111111111101 (
b1000000 .
b1001010000110100000101010 ,
b0 )
#570
0!
#575
1"
#577
b11111111111111111111111111111101 0
b11111111111111111111111111111001 /
b110000000101010 1
b101100 3
b1000010010110000000101010 2
b0 6
b1000000 8
b1001010000110100000101010 7
#580
0"
#585
1!
#587
b100001001011000000010101000 -
b11000000011010100 +
b11111111111111111111111111111101 *
b11111111111111111111111111111001 (
b101100 .
b1000010010110000000101010 ,
b1 )
b110000 <
b0 4
b110000 5
0:
#590
0!
#595
1"
#597
b1 6
b101100 8
b1000010010110000000101010 7
b0 0
b0 /
b0 1
b110000 3
b0 2
#600
0"
#605
1!
#607
b110100 <
b10001100000000000000000000111 4
b110100 5
b0 -
b110000 +
b0 *
b0 (
b110000 .
b0 ,
b0 )
#610
0!
#615
1"
#617
b1 /
b111 1
b110100 3
b10001100000000000000000000111 2
b0 6
b110000 8
b0 7
#620
0"
#625
1!
#627
b110000000000000000000011100 -
b1010000 +
b1 (
b110100 .
b10001100000000000000000000111 ,
b1 )
b111000 <
b100001001010011111111111111111 4
b111000 5
#630
0!
#635
1"
#637
b1 6
b110100 8
b10001100000000000000000000111 7
b11111111111111111111111111111101 0
b11111111111111111111111111111101 /
b11111111111111111111111111111111 1
b111000 3
b100001001010011111111111111111 2
#640
0"
#645
1!
#647
b111100 <
b1000000000000000000000001010 4
b111100 5
b100101001111111111111111100 -
b110100 +
b11111111111111111111111111111101 *
b11111111111111111111111111111101 (
b111000 .
b100001001010011111111111111111 ,
b11111111111111111111111111111100 )
#650
0!
#655
1"
#657
b0 0
b0 /
b1010 1
b111100 3
b1000000000000000000000001010 2
b11111111111111111111111111111100 6
b111000 8
b100001001010011111111111111111 7
#660
0"
#665
1!
#667
b101000 -
b1100100 +
b0 *
b0 (
b111100 .
b1000000000000000000000001010 ,
b11011110101011011011111011101111 )
b1000000 <
b1001010000110100000101010 4
b1000000 5
#670
0!
#675
1"
#677
b11011110101011011011111011101111 6
b111100 8
b1000000000000000000000001010 7
b11111111111111111111111111111001 0
b11111111111111111111111111111100 /
b110100000101010 1
b1000000 3
b1001010000110100000101010 2
#680
0"
#685
1!
#687
1:
b101100 <
b1000010010110000000101010 4
b101100 5
b100101000011010000010101000 -
b11010000011101000 +
b11111111111111111111111111111001 *
b11111111111111111111111111111100 (
b1000000 .
b1001010000110100000101010 ,
b0 )
#690
0!
#695
1"
#697
b11111111111111111111111111111100 0
b11111111111111111111111111111001 /
b110000000101010 1
b101100 3
b1000010010110000000101010 2
b0 6
b1000000 8
b1001010000110100000101010 7
#700
0"
#705
1!
#707
b100001001011000000010101000 -
b11000000011010100 +
b11111111111111111111111111111100 *
b11111111111111111111111111111001 (
b101100 .
b1000010010110000000101010 ,
b1 )
b110000 <
b0 4
b110000 5
0:
#710
0!
#715
1"
#717
b1 6
b101100 8
b1000010010110000000101010 7
b0 0
b0 /
b0 1
b110000 3
b0 2
#720
0"
#725
1!
#727
b110100 <
b10001100000000000000000000111 4
b110100 5
b0 -
b110000 +
b0 *
b0 (
b110000 .
b0 ,
b0 )
#730
0!
#735
1"
#737
b1 /
b111 1
b110100 3
b10001100000000000000000000111 2
b0 6
b110000 8
b0 7
#740
0"
#745
1!
#747
b110000000000000000000011100 -
b1010000 +
b1 (
b110100 .
b10001100000000000000000000111 ,
b1 )
b111000 <
b100001001010011111111111111111 4
b111000 5
#750
0!
#755
1"
#757
b1 6
b110100 8
b10001100000000000000000000111 7
b11111111111111111111111111111100 0
b11111111111111111111111111111100 /
b11111111111111111111111111111111 1
b111000 3
b100001001010011111111111111111 2
#760
0"
#765
1!
#767
b111100 <
b1000000000000000000000001010 4
b111100 5
b100101001111111111111111100 -
b110100 +
b11111111111111111111111111111100 *
b11111111111111111111111111111100 (
b111000 .
b100001001010011111111111111111 ,
b11111111111111111111111111111011 )
#770
0!
#775
1"
#777
b0 0
b0 /
b1010 1
b111100 3
b1000000000000000000000001010 2
b11111111111111111111111111111011 6
b111000 8
b100001001010011111111111111111 7
#780
0"
#785
1!
#787
b101000 -
b1100100 +
b0 *
b0 (
b111100 .
b1000000000000000000000001010 ,
b11011110101011011011111011101111 )
b1000000 <
b1001010000110100000101010 4
b1000000 5
#790
0!
#795
1"
#797
b11011110101011011011111011101111 6
b111100 8
b1000000000000000000000001010 7
b11111111111111111111111111111001 0
b11111111111111111111111111111011 /
b110100000101010 1
b1000000 3
b1001010000110100000101010 2
#800
0"
#805
1!
#807
1:
b101100 <
b1000010010110000000101010 4
b101100 5
b100101000011010000010101000 -
b11010000011101000 +
b11111111111111111111111111111001 *
b11111111111111111111111111111011 (
b1000000 .
b1001010000110100000101010 ,
b0 )
#810
0!
#815
1"
#817
b11111111111111111111111111111011 0
b11111111111111111111111111111001 /
b110000000101010 1
b101100 3
b1000010010110000000101010 2
b0 6
b1000000 8
b1001010000110100000101010 7
#820
0"
#825
1!
#827
b100001001011000000010101000 -
b11000000011010100 +
b11111111111111111111111111111011 *
b11111111111111111111111111111001 (
b101100 .
b1000010010110000000101010 ,
b1 )
b110000 <
b0 4
b110000 5
0:
#830
0!
#835
1"
#837
b1 6
b101100 8
b1000010010110000000101010 7
b0 0
b0 /
b0 1
b110000 3
b0 2
#840
0"
#845
1!
#847
b110100 <
b10001100000000000000000000111 4
b110100 5
b0 -
b110000 +
b0 *
b0 (
b110000 .
b0 ,
b0 )
#850
0!
#855
1"
#857
b1 /
b111 1
b110100 3
b10001100000000000000000000111 2
b0 6
b110000 8
b0 7
#860
0"
#865
1!
#867
b110000000000000000000011100 -
b1010000 +
b1 (
b110100 .
b10001100000000000000000000111 ,
b1 )
b111000 <
b100001001010011111111111111111 4
b111000 5
#870
0!
#875
1"
#877
b1 6
b110100 8
b10001100000000000000000000111 7
b11111111111111111111111111111011 0
b11111111111111111111111111111011 /
b11111111111111111111111111111111 1
b111000 3
b100001001010011111111111111111 2
#880
0"
#885
1!
#887
b111100 <
b1000000000000000000000001010 4
b111100 5
b100101001111111111111111100 -
b110100 +
b11111111111111111111111111111011 *
b11111111111111111111111111111011 (
b111000 .
b100001001010011111111111111111 ,
b11111111111111111111111111111010 )
#890
0!
#895
1"
#897
b0 0
b0 /
b1010 1
b111100 3
b1000000000000000000000001010 2
b11111111111111111111111111111010 6
b111000 8
b100001001010011111111111111111 7
#900
0"
#905
1!
#907
b101000 -
b1100100 +
b0 *
b0 (
b111100 .
b1000000000000000000000001010 ,
b11011110101011011011111011101111 )
b1000000 <
b1001010000110100000101010 4
b1000000 5
#910
0!
#915
1"
#917
b11011110101011011011111011101111 6
b111100 8
b1000000000000000000000001010 7
b11111111111111111111111111111001 0
b11111111111111111111111111111010 /
b110100000101010 1
b1000000 3
b1001010000110100000101010 2
#920
0"
#925
1!
#927
1:
b101100 <
b1000010010110000000101010 4
b101100 5
b100101000011010000010101000 -
b11010000011101000 +
b11111111111111111111111111111001 *
b11111111111111111111111111111010 (
b1000000 .
b1001010000110100000101010 ,
b0 )
#930
0!
#935
1"
#937
b11111111111111111111111111111010 0
b11111111111111111111111111111001 /
b110000000101010 1
b101100 3
b1000010010110000000101010 2
b0 6
b1000000 8
b1001010000110100000101010 7
#940
0"
#945
1!
#947
b100001001011000000010101000 -
b11000000011010100 +
b11111111111111111111111111111010 *
b11111111111111111111111111111001 (
b101100 .
b1000010010110000000101010 ,
b1 )
b110000 <
b0 4
b110000 5
0:
#950
0!
#955
1"
#957
b1 6
b101100 8
b1000010010110000000101010 7
b0 0
b0 /
b0 1
b110000 3
b0 2
#960
0"
#965
1!
#967
b110100 <
b10001100000000000000000000111 4
b110100 5
b0 -
b110000 +
b0 *
b0 (
b110000 .
b0 ,
b0 )
#970
0!
#975
1"
#977
b1 /
b111 1
b110100 3
b10001100000000000000000000111 2
b0 6
b110000 8
b0 7
#980
0"
#985
1!
#987
b110000000000000000000011100 -
b1010000 +
b1 (
b110100 .
b10001100000000000000000000111 ,
b1 )
b111000 <
b100001001010011111111111111111 4
b111000 5
#990
0!
#995
1"
#997
b1 6
b110100 8
b10001100000000000000000000111 7
b11111111111111111111111111111010 0
b11111111111111111111111111111010 /
b11111111111111111111111111111111 1
b111000 3
b100001001010011111111111111111 2
#1000
0"
#1005
1!
#1007
b111100 <
b1000000000000000000000001010 4
b111100 5
b100101001111111111111111100 -
b110100 +
b11111111111111111111111111111010 *
b11111111111111111111111111111010 (
b111000 .
b100001001010011111111111111111 ,
b11111111111111111111111111111001 )
#1010
0!
#1015
1"
#1017
b0 0
b0 /
b1010 1
b111100 3
b1000000000000000000000001010 2
b11111111111111111111111111111001 6
b111000 8
b100001001010011111111111111111 7
#1020
0"
#1025
1!
#1027
b101000 -
b1100100 +
b0 *
b0 (
b111100 .
b1000000000000000000000001010 ,
b11011110101011011011111011101111 )
b1000000 <
b1001010000110100000101010 4
b1000000 5
#1030
0!
#1035
1"
#1037
b11011110101011011011111011101111 6
b111100 8
b1000000000000000000000001010 7
b11111111111111111111111111111001 0
b11111111111111111111111111111001 /
b110100000101010 1
b1000000 3
b1001010000110100000101010 2
#1040
0"
#1045
1!
